{"cameraMode":{"drawMode":0,"name":"Shaded","section":"Shading Mode"},"sceneLighting":false,"audioPlay":false,"sceneViewState":{"m_AlwaysRefresh":false,"showFog":true,"showSkybox":false,"showFlares":true,"showImageEffects":true,"showParticleSystems":true,"showVisualEffectGraphs":true,"m_FxEnabled":true},"in2DMode":false,"pivot":{"x":-14.967065811157227,"y":-3.4052162170410158,"z":9.940401077270508},"rotation":{"x":0.08596393465995789,"y":-0.4705010652542114,"z":0.04629532992839813,"w":0.8768521547317505},"size":10.0,"orthographic":false}